CHANGELOG.md
CODE_OF_CONDUCT.md
CONTRIBUTING.md
LICENSE
LICENSE_weights
MANIFEST.in
Makefile
README.md
mypy.ini
requirements.txt
setup.cfg
setup.py
assets/a_duck_quacking_as_birds_chirp_and_a_pigeon_cooing.mp3
assets/bach.mp3
assets/bolero_ravel.mp3
assets/sirens_and_a_humming_engine_approach_and_pass.mp3
audiocraft/__init__.py
audiocraft/environment.py
audiocraft/py.typed
audiocraft/train.py
audiocraft.egg-info/PKG-INFO
audiocraft.egg-info/SOURCES.txt
audiocraft.egg-info/dependency_links.txt
audiocraft.egg-info/requires.txt
audiocraft.egg-info/top_level.txt
audiocraft/adversarial/__init__.py
audiocraft/adversarial/losses.py
audiocraft/adversarial/discriminators/__init__.py
audiocraft/adversarial/discriminators/base.py
audiocraft/adversarial/discriminators/mpd.py
audiocraft/adversarial/discriminators/msd.py
audiocraft/adversarial/discriminators/msstftd.py
audiocraft/data/__init__.py
audiocraft/data/audio.py
audiocraft/data/audio_dataset.py
audiocraft/data/audio_utils.py
audiocraft/data/info_audio_dataset.py
audiocraft/data/music_dataset.py
audiocraft/data/sound_dataset.py
audiocraft/data/zip.py
audiocraft/grids/__init__.py
audiocraft/grids/_base_explorers.py
audiocraft/grids/audiogen/__init__.py
audiocraft/grids/audiogen/audiogen_base_16khz.py
audiocraft/grids/audiogen/audiogen_pretrained_16khz_eval.py
audiocraft/grids/compression/__init__.py
audiocraft/grids/compression/_explorers.py
audiocraft/grids/compression/debug.py
audiocraft/grids/compression/encodec_audiogen_16khz.py
audiocraft/grids/compression/encodec_base_24khz.py
audiocraft/grids/compression/encodec_musicgen_32khz.py
audiocraft/grids/diffusion/4_bands_base_32khz.py
audiocraft/grids/diffusion/__init__.py
audiocraft/grids/diffusion/_explorers.py
audiocraft/grids/musicgen/__init__.py
audiocraft/grids/musicgen/_explorers.py
audiocraft/grids/musicgen/musicgen_base_32khz.py
audiocraft/grids/musicgen/musicgen_base_cached_32khz.py
audiocraft/grids/musicgen/musicgen_clapemb_32khz.py
audiocraft/grids/musicgen/musicgen_melody_32khz.py
audiocraft/grids/musicgen/musicgen_pretrained_32khz_eval.py
audiocraft/grids/musicgen/musicgen_stereo_finetune_32khz.py
