Metadata-Version: 2.1
Name: audiocraft
Version: 1.2.0
Summary: Audio generation research library for PyTorch
Home-page: https://github.com/facebookresearch/audiocraft
Author: FAIR Speech & Audio
Author-email: defossez@meta.com, jadecopet@meta.com
License: MIT License
Classifier: License :: OSI Approved :: MIT License
Classifier: Topic :: Multimedia :: Sound/Audio
Classifier: Topic :: Scientific/Engineering :: Artificial Intelligence
Requires-Python: >=3.8.0
License-File: LICENSE
License-File: LICENSE_weights
Requires-Dist: av
Requires-Dist: einops
Requires-Dist: flashy>=0.0.1
Requires-Dist: hydra-core>=1.1
Requires-Dist: hydra_colorlog
Requires-Dist: julius
Requires-Dist: num2words
Requires-Dist: numpy
Requires-Dist: sentencepiece
Requires-Dist: spacy>=3.6.1
Requires-Dist: torch==2.1.0
Requires-Dist: torchaudio>=2.0.0
Requires-Dist: huggingface_hub
Requires-Dist: tqdm
Requires-Dist: transformers>=4.31.0
Requires-Dist: xformers
Requires-Dist: demucs
Requires-Dist: librosa
Requires-Dist: gradio
Requires-Dist: torchmetrics
Requires-Dist: encodec
Requires-Dist: protobuf
Provides-Extra: dev
Requires-Dist: coverage; extra == "dev"
Requires-Dist: flake8; extra == "dev"
Requires-Dist: mypy; extra == "dev"
Requires-Dist: pdoc3; extra == "dev"
Requires-Dist: pytest; extra == "dev"
